ant/__init__.py
ant/logger.py
ant/rpc_call_helper.py
protocol/__init__.py
protocol/common_pb2.py
protocol/service_method.py
protocol/account/__init__.py
protocol/account/account_req_helper.py
protocol/quote/__init__.py
protocol/quote/mdsquote_pb2.py
protocol/quote/quote_enum_pb2.py
protocol/quote/quote_pb2.py
protocol/quote/quote_req_helper.py
protocol/trade/__init__.py
protocol/trade/trade_enum_pb2.py
protocol/trade/trade_futures_pb2.py
protocol/trade/trade_pb2.py
protocol/trade/trade_req_helper.py
protocol/trade/trade_stock_pb2.py
testczh-0.2.8.dist-info/LICENSE
testczh-0.2.8.dist-info/METADATA
testczh-0.2.8.dist-info/WHEEL
testczh-0.2.8.dist-info/top_level.txt
testczh-0.2.8.dist-info/RECORD
