Metadata-Version: 2.1
Name: testczh
Version: 0.2.8
Summary: No description.
Home-page: UNKNOWN
Author: czh
Author-email: 1040791159@qq.com
License: UNKNOWN
Platform: UNKNOWN
Classifier: Programming Language :: Python :: 3.8
Classifier: License :: OSI Approved :: MIT License
Classifier: Operating System :: Microsoft :: Windows :: Windows 7
Requires-Dist: protobuf
